toggl/__init__.py
toggl/_client.py
toggl/_client_base.py
toggl/_exceptions.py
toggl/_models.py
toggl/_resource.py
toggl/_response.py
toggl/_schemas.py
toggl/_types.py
toggl/object_model/__init__.py
toggl/object_model/_object_model_base.py
toggl/object_model/find.py
toggl/object_model/operators.py
toggl/object_model/project.py
toggl/object_model/time_entry.py
toggl/resources/__init__.py
toggl/resources/_request_schemas.py
toggl/resources/_response_schemas.py
toggl/resources/me/__init__.py
toggl/resources/me/_me.py
toggl/resources/me/clients/__init__.py
toggl/resources/me/clients/_clients.py
toggl/resources/me/clients/schemas.py
toggl/resources/me/features/__init__.py
toggl/resources/me/features/_features.py
toggl/resources/me/features/schemas.py
toggl/resources/me/location/__init__.py
toggl/resources/me/location/_location.py
toggl/resources/me/location/schemas.py
toggl/resources/me/logged/__init__.py
toggl/resources/me/logged/_logged.py
toggl/resources/me/logged/schemas.py
toggl/resources/me/organizations/__init__.py
toggl/resources/me/organizations/_organizations.py
toggl/resources/me/organizations/schemas.py
toggl/resources/me/preferences/__init__.py
toggl/resources/me/preferences/_preferences.py
toggl/resources/me/preferences/schemas.py
toggl/resources/me/projects/__init__.py
toggl/resources/me/projects/_projects.py
toggl/resources/me/projects/paginated/__init__.py
toggl/resources/me/projects/paginated/_paginated.py
toggl/resources/me/projects/paginated/schemas.py
toggl/resources/me/projects/schemas.py
toggl/resources/me/quota/__init__.py
toggl/resources/me/quota/_quota.py
toggl/resources/me/quota/schemas.py
toggl/resources/me/schemas.py
toggl/resources/me/tags/__init__.py
toggl/resources/me/tags/_tags.py
toggl/resources/me/tags/schemas.py
toggl/resources/me/tasks/__init__.py
toggl/resources/me/tasks/_tasks.py
toggl/resources/me/tasks/schemas.py
toggl/resources/me/time_entries/_time_entries.py
toggl/resources/me/time_entries/current/__init__.py
toggl_api_python-0.0.6.dist-info/WHEEL
toggl_api_python-0.0.6.dist-info/METADATA
toggl_api_python-0.0.6.dist-info/RECORD
