Metadata-Version: 2.3
Name: toggl-api-python
Version: 0.0.6
Requires-Dist: httpx>=0.28.1
Requires-Dist: pydantic==2.8.2
Requires-Python: >=3.12
